web3_data_tools/__init__.py
web3_data_tools/_modidx.py
web3_data_tools/core.py
web3_data_tools/mev_boost.py
web3_data_tools/web3.py
web3_data_tools-1.2.0.dist-info/LICENSE
web3_data_tools-1.2.0.dist-info/METADATA
web3_data_tools-1.2.0.dist-info/WHEEL
web3_data_tools-1.2.0.dist-info/entry_points.txt
web3_data_tools-1.2.0.dist-info/top_level.txt
web3_data_tools-1.2.0.dist-info/RECORD
