Metadata-Version: 2.1
Name: web3-data-tools
Version: 1.2.0
Summary: Data tools for Web3
Home-page: https://github.com/flashbots/web3-data-tools
Author: Andres Babino
Author-email: ababino@gmail.com
License: Apache Software License 2.0
Keywords: nbdev jupyter notebook python
Classifier: Development Status :: 4 - Beta
Classifier: Intended Audience :: Developers
Classifier: Natural Language :: English
Classifier: Programming Language :: Python :: 3.7
Classifier: Programming Language :: Python :: 3.8
Classifier: Programming Language :: Python :: 3.9
Classifier: Programming Language :: Python :: 3.10
Classifier: License :: OSI Approved :: Apache Software License
Requires-Python: >=3.7
License-File: LICENSE
Requires-Dist: web3
Requires-Dist: pandas
Requires-Dist: fastcore
Provides-Extra: dev
